{
  "platform" : "iOS",
  "device" : "iPhone",
  "sessionId" : "vpioBypassAFE_6x_0329_115647",
  "engine" : "vpioBypassAFE",
  "deviceId" : "B1FC5AC2-EDE1-474A-A1B2-7FC0519289C8",
  "timestamp" : 1774821498,
  "trials" : [
    {
      "totalResponseCount" : 1,
      "snrDb" : 0,
      "timeToSpeakerMs" : 0,
      "erlDb" : 40.615348815917969,
      "estimatedMOS" : 5,
      "notes" : "Max",
      "engineDisplayName" : "VPIO Bypass + AFE",
      "selfInterruptCount" : 0,
      "timestamp" : 1774821498,
      "bargeInCount" : 0,
      "deviceName" : "iPhone",
      "engine" : "vpioBypassAFE",
      "trialIndex" : 0,
      "firstAudioLatencyMs" : 403,
      "hasQualityMetrics" : true
    },
    {
      "totalResponseCount" : 2,
      "deviceName" : "iPhone",
      "firstAudioLatencyMs" : 504,
      "snrDb" : 0,
      "engine" : "vpioBypassAFE",
      "notes" : "Max",
      "timestamp" : 1774821498,
      "selfInterruptCount" : 0,
      "estimatedMOS" : 5,
      "timeToSpeakerMs" : 0,
      "erlDb" : 42.917804718017578,
      "hasQualityMetrics" : true,
      "bargeInCount" : 1,
      "trialIndex" : 1,
      "engineDisplayName" : "VPIO Bypass + AFE"
    },
    {
      "bargeInCount" : 0,
      "erlDb" : 35.481029510498047,
      "firstAudioLatencyMs" : 604,
      "notes" : "Max",
      "timestamp" : 1774821498,
      "snrDb" : 0,
      "engineDisplayName" : "VPIO Bypass + AFE",
      "trialIndex" : 2,
      "deviceName" : "iPhone",
      "hasQualityMetrics" : true,
      "estimatedMOS" : 5,
      "timeToSpeakerMs" : 0,
      "totalResponseCount" : 2,
      "engine" : "vpioBypassAFE",
      "selfInterruptCount" : 1
    },
    {
      "engine" : "vpioBypassAFE",
      "estimatedMOS" : 5,
      "hasQualityMetrics" : true,
      "erlDb" : 75.982032775878906,
      "timeToSpeakerMs" : 0,
      "notes" : "Max",
      "bargeInCount" : 0,
      "selfInterruptCount" : 0,
      "deviceName" : "iPhone",
      "trialIndex" : 3,
      "timestamp" : 1774821498,
      "engineDisplayName" : "VPIO Bypass + AFE",
      "snrDb" : 0,
      "firstAudioLatencyMs" : 599,
      "totalResponseCount" : 1
    },
    {
      "notes" : "Max",
      "timestamp" : 1774821498,
      "bargeInCount" : 0,
      "selfInterruptCount" : 0,
      "totalResponseCount" : 1,
      "hasQualityMetrics" : true,
      "erlDb" : 23.437177658081055,
      "engineDisplayName" : "VPIO Bypass + AFE",
      "firstAudioLatencyMs" : 561,
      "engine" : "vpioBypassAFE",
      "snrDb" : 0,
      "timeToSpeakerMs" : 0,
      "deviceName" : "iPhone",
      "estimatedMOS" : 5,
      "trialIndex" : 4
    },
    {
      "timestamp" : 1774821498,
      "notes" : "Max",
      "erlDb" : 79.019783020019531,
      "deviceName" : "iPhone",
      "timeToSpeakerMs" : 0,
      "estimatedMOS" : 5,
      "engine" : "vpioBypassAFE",
      "trialIndex" : 5,
      "hasQualityMetrics" : true,
      "totalResponseCount" : 1,
      "engineDisplayName" : "VPIO Bypass + AFE",
      "bargeInCount" : 0,
      "firstAudioLatencyMs" : 417,
      "selfInterruptCount" : 0,
      "snrDb" : 0
    }
  ],
  "trialCount" : 6,
  "engineDisplayName" : "VPIO Bypass + AFE"
}